bg_remove/__init__.py
bg_remove/main.py
bgrev/__init__.py
bgrev/main.py
bgrev-0.1.0.dist-info/METADATA
bgrev-0.1.0.dist-info/WHEEL
bgrev-0.1.0.dist-info/top_level.txt
bgrev-0.1.0.dist-info/RECORD
